pytubefix/__init__.py
pytubefix/__main__.py
pytubefix/async_http_client.py
pytubefix/async_youtube.py
pytubefix/buffer.py
pytubefix/captions.py
pytubefix/chapters.py
pytubefix/cipher.py
pytubefix/cli.py
pytubefix/exceptions.py
pytubefix/extract.py
pytubefix/file_system.py
pytubefix/helpers.py
pytubefix/info.py
pytubefix/innertube.py
pytubefix/itags.py
pytubefix/jsinterp.py
pytubefix/keymoments.py
pytubefix/metadata.py
pytubefix/monostate.py
pytubefix/parser.py
pytubefix/protobuf.py
pytubefix/query.py
pytubefix/request.py
pytubefix/streams.py
pytubefix/version.py
pytubefix/botGuard/__init__.py
pytubefix/botGuard/bot_guard.py
pytubefix/botGuard/vm/botGuard.js
pytubefix/contrib/__init__.py
pytubefix/contrib/channel.py
pytubefix/contrib/playlist.py
pytubefix/contrib/search.py
pytubefix/sabr/__init__.py
pytubefix/sabr/common.py
pytubefix/sabr/proto.py
pytubefix/sabr/core/UMP.py
pytubefix/sabr/core/__init__.py
pytubefix/sabr/core/chunked_data_buffer.py
pytubefix/sabr/core/server_abr_stream.py
pytubefix/sabr/video_streaming/__init__.py
pytubefix/sabr/video_streaming/buffered_range.py
pytubefix/sabr/video_streaming/client_abr_state.py
pytubefix/sabr/video_streaming/format_initialization_metadata.py
pytubefix/sabr/video_streaming/media_header.py
pytubefix/sabr/video_streaming/next_request_policy.py
pytubefix/sabr/video_streaming/playback_cookie.py
pytubefix/sabr/video_streaming/sabr_error.py
pytubefix/sabr/video_streaming/sabr_redirect.py
pytubefix/sabr/video_streaming/stream_protection_status.py
pytubefix/sabr/video_streaming/streamer_context.py
pytubefix/sabr/video_streaming/time_range.py
pytubefix/sabr/video_streaming/video_playback_abr_request.py
pytubefix/sig_nsig/__init__.py
pytubefix/sig_nsig/node_runner.py
pytubefix/sig_nsig/vm/runner.js
pytubefix_sakib-10.3.6.dist-info/licenses/LICENSE
pytubefix_sakib-10.3.6.dist-info/METADATA
pytubefix_sakib-10.3.6.dist-info/WHEEL
pytubefix_sakib-10.3.6.dist-info/entry_points.txt
pytubefix_sakib-10.3.6.dist-info/top_level.txt
pytubefix_sakib-10.3.6.dist-info/RECORD
