Metadata-Version: 2.4
Name: pytubefix-sakib
Version: 10.3.6
Summary: A maintained fork of pytubefix with additional fixes
Author-email: Juan Bindez <juanbindez780@gmail.com>, Nazmus Sakib <sakibkuet16@gmail.com>
License: MIT license
Project-URL: Upstream Project, https://github.com/juanbindez/pytubefix
Project-URL: Homepage, https://github.com/Sakib75/pytubefix
Project-URL: Bug Reports, https://github.com/Sakib75/pytubefix/issues
Keywords: youtube,download,video,stream
Requires-Python: >=3.7
License-File: LICENSE
Requires-Dist: aiohttp>=3.12.13
Requires-Dist: nodejs-wheel-binaries>=22.20.0
Dynamic: license-file
